robustify/__init__.py
robustify/error.py
robustify/functional.py
robustify/result.py
robustify-0.1.5.dist-info/METADATA
robustify-0.1.5.dist-info/WHEEL
robustify-0.1.5.dist-info/licenses/LICENSE
robustify-0.1.5.dist-info/RECORD
